{
  "data": {
    "article": {},
    "attachments": {
      "media_keys": [
        "3_2040830318895394816"
      ],
      "media_source_tweet_id": [
        "2040830326440628579"
      ]
    },
    "author_id": "1804875241367433216",
    "context_annotations": [
      {
        "domain": {
          "description": "Categories within Brand Verticals that narrow down the scope of Brands",
          "id": "46",
          "name": "Business Taxonomy"
        },
        "entity": {
          "description": "Brands, companies, advertisers and every non-person handle with the profit intent related to offline and online games such as gaming consoles, tabletop games, video game publishers",
          "id": "1557696940178935808",
          "name": "Gaming Business"
        }
      }
    ],
    "conversation_id": "2041365035424072123",
    "created_at": "2026-04-07T03:58:45.000Z",
    "edit_controls": {
      "editable_until": "2026-04-07T04:58:45.000Z",
      "edits_remaining": 5,
      "is_edit_eligible": false
    },
    "edit_history_tweet_ids": [
      "2041365035424072123"
    ],
    "entities": {
      "mentions": [
        {
          "end": 19,
          "id": "1847403676958134272",
          "start": 3,
          "username": "HoneyNoodleSoup"
        }
      ],
      "urls": [
        {
          "display_url": "pic.x.com/LZNQuE5nO2",
          "end": 44,
          "expanded_url": "https://x.com/HoneyNoodleSoup/status/2040830326440628579/photo/1",
          "media_key": "3_2040830318895394816",
          "start": 21,
          "url": "https://t.co/LZNQuE5nO2"
        }
      ]
    },
    "geo": {},
    "id": "2041365035424072123",
    "lang": "zxx",
    "note_tweet": {
      "entities": {}
    },
    "possibly_sensitive": false,
    "public_metrics": {
      "bookmark_count": 0,
      "impression_count": 0,
      "like_count": 0,
      "quote_count": 0,
      "reply_count": 0,
      "retweet_count": 990
    },
    "referenced_tweets": [
      {
        "id": "2040830326440628579",
        "type": "retweeted"
      }
    ],
    "reply_settings": "everyone",
    "text": "RT @HoneyNoodleSoup: https://t.co/LZNQuE5nO2"
  },
  "includes": {
    "media": [
      {
        "height": 1075,
        "media_key": "3_2040830318895394816",
        "public_metrics": {},
        "type": "photo",
        "url": "https://pbs.twimg.com/media/HFJ8XLybcAApzZW.jpg",
        "width": 1080
      }
    ],
    "tweets": [
      {
        "article": {},
        "attachments": {
          "media_keys": [
            "3_2040830318895394816"
          ],
          "media_source_tweet_id": [
            "2040830326440628579"
          ]
        },
        "author_id": "1804875241367433216",
        "context_annotations": [
          {
            "domain": {
              "description": "Categories within Brand Verticals that narrow down the scope of Brands",
              "id": "46",
              "name": "Business Taxonomy"
            },
            "entity": {
              "description": "Brands, companies, advertisers and every non-person handle with the profit intent related to offline and online games such as gaming consoles, tabletop games, video game publishers",
              "id": "1557696940178935808",
              "name": "Gaming Business"
            }
          }
        ],
        "conversation_id": "2041365035424072123",
        "created_at": "2026-04-07T03:58:45.000Z",
        "edit_controls": {
          "editable_until": "2026-04-07T04:58:45.000Z",
          "edits_remaining": 5,
          "is_edit_eligible": false
        },
        "edit_history_tweet_ids": [
          "2041365035424072123"
        ],
        "entities": {
          "mentions": [
            {
              "end": 19,
              "id": "1847403676958134272",
              "start": 3,
              "username": "HoneyNoodleSoup"
            }
          ],
          "urls": [
            {
              "display_url": "pic.x.com/LZNQuE5nO2",
              "end": 44,
              "expanded_url": "https://x.com/HoneyNoodleSoup/status/2040830326440628579/photo/1",
              "media_key": "3_2040830318895394816",
              "start": 21,
              "url": "https://t.co/LZNQuE5nO2"
            }
          ]
        },
        "geo": {},
        "id": "2041365035424072123",
        "lang": "zxx",
        "note_tweet": {
          "entities": {}
        },
        "possibly_sensitive": false,
        "public_metrics": {
          "bookmark_count": 0,
          "impression_count": 0,
          "like_count": 0,
          "quote_count": 0,
          "reply_count": 0,
          "retweet_count": 990
        },
        "referenced_tweets": [
          {
            "id": "2040830326440628579",
            "type": "retweeted"
          }
        ],
        "reply_settings": "everyone",
        "text": "RT @HoneyNoodleSoup: https://t.co/LZNQuE5nO2"
      },
      {
        "article": {},
        "attachments": {
          "media_keys": [
            "3_2040830318895394816"
          ]
        },
        "author_id": "1847403676958134272",
        "context_annotations": [
          {
            "domain": {
              "description": "Categories within Brand Verticals that narrow down the scope of Brands",
              "id": "46",
              "name": "Business Taxonomy"
            },
            "entity": {
              "description": "Brands, companies, advertisers and every non-person handle with the profit intent related to offline and online games such as gaming consoles, tabletop games, video game publishers",
              "id": "1557696940178935808",
              "name": "Gaming Business"
            }
          }
        ],
        "conversation_id": "2040830326440628579",
        "created_at": "2026-04-05T16:34:01.000Z",
        "edit_controls": {
          "editable_until": "2026-04-05T17:34:01.000Z",
          "edits_remaining": 5,
          "is_edit_eligible": true
        },
        "edit_history_tweet_ids": [
          "2040830326440628579"
        ],
        "entities": {
          "urls": [
            {
              "display_url": "pic.x.com/LZNQuE5nO2",
              "end": 23,
              "expanded_url": "https://x.com/HoneyNoodleSoup/status/2040830326440628579/photo/1",
              "media_key": "3_2040830318895394816",
              "start": 0,
              "url": "https://t.co/LZNQuE5nO2"
            }
          ]
        },
        "geo": {},
        "id": "2040830326440628579",
        "lang": "zxx",
        "note_tweet": {
          "entities": {}
        },
        "possibly_sensitive": false,
        "public_metrics": {
          "bookmark_count": 269,
          "impression_count": 35544,
          "like_count": 4196,
          "quote_count": 13,
          "reply_count": 5,
          "retweet_count": 990
        },
        "reply_settings": "everyone",
        "text": "https://t.co/LZNQuE5nO2"
      }
    ],
    "users": [
      {
        "created_at": "2024-06-23T13:53:01.000Z",
        "description": "⊹ 𝚜𝚞𝚣𝚞𝚖𝚎 ⊹ 逃避墙内把x当家版⌇𝟢𝟧⌇天使界隈⌇水色界隈 🫧\nメンヘラ  ✟  依存症  ✟  OD ✟ お掃除 💉\n​*⑅୨୧  無言フォローでお迎え​  ୨୧⑅* \n仲良くしてくれる子 DM待ってます 💤\n​他担・他界隈様  ◎  同担  ◎( 恋愛不可 🆖)",
        "entities": {
          "url": {
            "urls": [
              {
                "display_url": "ngl.link/aberyoheiskm",
                "end": 23,
                "expanded_url": "https://ngl.link/aberyoheiskm",
                "start": 0,
                "url": "https://t.co/gj0HdlxzyS"
              }
            ]
          }
        },
        "id": "1804875241367433216",
        "location": "キラキラな世界ʚ✞ɞ ",
        "name": "⊹すずめ⊹🩵",
        "pinned_tweet_id": "2040494384823874007",
        "profile_image_url": "https://pbs.twimg.com/profile_images/2040630139747553280/HymSNJZ__normal.jpg",
        "protected": false,
        "public_metrics": {
          "followers_count": 18,
          "following_count": 97,
          "like_count": 443,
          "listed_count": 0,
          "media_count": 31,
          "tweet_count": 331
        },
        "url": "https://t.co/gj0HdlxzyS",
        "username": "aberyoheiskm",
        "verified": true
      },
      {
        "created_at": "2024-10-18T22:26:21.000Z",
        "description": "stupid cat girl🐾",
        "entities": {
          "url": {
            "urls": [
              {
                "display_url": "ko-fi.com/merunoodle",
                "end": 23,
                "expanded_url": "https://ko-fi.com/merunoodle",
                "start": 0,
                "url": "https://t.co/OYbLYnXHdb"
              }
            ]
          }
        },
        "id": "1847403676958134272",
        "location": "dm fee: cat pics",
        "name": "𝐦𝐞𝐫𝐮 𝐮𝐰𝐮",
        "pinned_tweet_id": "1960085963796779465",
        "profile_image_url": "https://pbs.twimg.com/profile_images/2025056087590793216/56D960xt_normal.jpg",
        "protected": false,
        "public_metrics": {
          "followers_count": 3028,
          "following_count": 533,
          "like_count": 6092,
          "listed_count": 6,
          "media_count": 178,
          "tweet_count": 1960
        },
        "url": "https://t.co/OYbLYnXHdb",
        "username": "HoneyNoodleSoup",
        "verified": false
      }
    ]
  }
}