{
  "data": {
    "article": {},
    "attachments": {
      "media_keys": [
        "3_2051972674084347904",
        "3_2051972673484537856"
      ]
    },
    "author_id": "1804875241367433216",
    "conversation_id": "2051972677385302347",
    "created_at": "2026-05-06T10:29:44.000Z",
    "edit_controls": {
      "editable_until": "2026-05-06T11:29:44.000Z",
      "edits_remaining": 5,
      "is_edit_eligible": true
    },
    "edit_history_tweet_ids": [
      "2051972677385302347"
    ],
    "entities": {
      "urls": [
        {
          "display_url": "pic.x.com/NlD2xy1piJ",
          "end": 86,
          "expanded_url": "https://x.com/aberyoheiskm/status/2051972677385302347/photo/1",
          "media_key": "3_2051972674084347904",
          "start": 63,
          "url": "https://t.co/NlD2xy1piJ"
        },
        {
          "display_url": "pic.x.com/NlD2xy1piJ",
          "end": 86,
          "expanded_url": "https://x.com/aberyoheiskm/status/2051972677385302347/photo/1",
          "media_key": "3_2051972673484537856",
          "start": 63,
          "url": "https://t.co/NlD2xy1piJ"
        }
      ]
    },
    "geo": {},
    "id": "2051972677385302347",
    "lang": "zh",
    "note_tweet": {
      "entities": {}
    },
    "possibly_sensitive": false,
    "public_metrics": {
      "bookmark_count": 0,
      "impression_count": 0,
      "like_count": 0,
      "quote_count": 0,
      "reply_count": 0,
      "retweet_count": 0
    },
    "reply_settings": "everyone",
    "text": "真南蚌，今天又收到两条举报的……我的帖子也有人视奸翻找啊绷不住了\n我这下得自己去删帖了😭😭😭\n明明都是自己很喜欢的调色，，， https://t.co/NlD2xy1piJ"
  },
  "includes": {
    "media": [
      {
        "height": 2215,
        "media_key": "3_2051972674084347904",
        "public_metrics": {},
        "type": "photo",
        "url": "https://pbs.twimg.com/media/HHoSRnebIAApjJv.jpg",
        "width": 1080
      },
      {
        "height": 2259,
        "media_key": "3_2051972673484537856",
        "public_metrics": {},
        "type": "photo",
        "url": "https://pbs.twimg.com/media/HHoSRlPawAA-BOd.jpg",
        "width": 1080
      }
    ],
    "tweets": [
      {
        "article": {},
        "attachments": {
          "media_keys": [
            "3_2051972674084347904",
            "3_2051972673484537856"
          ]
        },
        "author_id": "1804875241367433216",
        "conversation_id": "2051972677385302347",
        "created_at": "2026-05-06T10:29:44.000Z",
        "edit_controls": {
          "editable_until": "2026-05-06T11:29:44.000Z",
          "edits_remaining": 5,
          "is_edit_eligible": true
        },
        "edit_history_tweet_ids": [
          "2051972677385302347"
        ],
        "entities": {
          "urls": [
            {
              "display_url": "pic.x.com/NlD2xy1piJ",
              "end": 86,
              "expanded_url": "https://x.com/aberyoheiskm/status/2051972677385302347/photo/1",
              "media_key": "3_2051972674084347904",
              "start": 63,
              "url": "https://t.co/NlD2xy1piJ"
            },
            {
              "display_url": "pic.x.com/NlD2xy1piJ",
              "end": 86,
              "expanded_url": "https://x.com/aberyoheiskm/status/2051972677385302347/photo/1",
              "media_key": "3_2051972673484537856",
              "start": 63,
              "url": "https://t.co/NlD2xy1piJ"
            }
          ]
        },
        "geo": {},
        "id": "2051972677385302347",
        "lang": "zh",
        "note_tweet": {
          "entities": {}
        },
        "possibly_sensitive": false,
        "public_metrics": {
          "bookmark_count": 0,
          "impression_count": 0,
          "like_count": 0,
          "quote_count": 0,
          "reply_count": 0,
          "retweet_count": 0
        },
        "reply_settings": "everyone",
        "text": "真南蚌，今天又收到两条举报的……我的帖子也有人视奸翻找啊绷不住了\n我这下得自己去删帖了😭😭😭\n明明都是自己很喜欢的调色，，， https://t.co/NlD2xy1piJ"
      }
    ],
    "users": [
      {
        "created_at": "2024-06-23T13:53:01.000Z",
        "description": "⊹ 𝚜𝚞𝚣𝚞𝚖𝚎 ⊹ 小号：@aberyoheiabe⌇𝟢𝟧⌇天使/水色界隈 🫧\nメンヘラ  ✟  依存症  ✟  OD ✟ お掃除 💉\n​*⑅୨୧  無言フォローでお迎え​  ୨୧⑅* \n仲良くしてくれる子 DM待ってます💤\n​他担・他界隈様◎同担◎( 恋愛不可 🆖)看成分互fo↓来玩提问箱！",
        "entities": {
          "description": {
            "mentions": [
              {
                "end": 27,
                "start": 14,
                "username": "aberyoheiabe"
              }
            ]
          },
          "url": {
            "urls": [
              {
                "display_url": "ngl.link/aberyoheiskm",
                "end": 23,
                "expanded_url": "https://ngl.link/aberyoheiskm",
                "start": 0,
                "url": "https://t.co/gj0HdlxzyS"
              }
            ]
          }
        },
        "id": "1804875241367433216",
        "location": "キラキラな世界ʚ✞ɞ ",
        "name": "⊹すずめ⊹🩵",
        "pinned_tweet_id": "2040494384823874007",
        "profile_image_url": "https://pbs.twimg.com/profile_images/2040630139747553280/HymSNJZ__normal.jpg",
        "protected": false,
        "public_metrics": {
          "followers_count": 195,
          "following_count": 244,
          "like_count": 2322,
          "listed_count": 1,
          "media_count": 121,
          "tweet_count": 1325
        },
        "url": "https://t.co/gj0HdlxzyS",
        "username": "aberyoheiskm",
        "verified": false
      }
    ]
  }
}