{
  "data": {
    "article": {},
    "attachments": {},
    "author_id": "1804875241367433216",
    "conversation_id": "2054008553992753563",
    "created_at": "2026-05-13T19:39:44.000Z",
    "edit_controls": {
      "editable_until": "2026-05-13T20:39:44.000Z",
      "edits_remaining": 5,
      "is_edit_eligible": false
    },
    "edit_history_tweet_ids": [
      "2054647801544683564"
    ],
    "entities": {
      "mentions": [
        {
          "end": 8,
          "id": "1426079620906975232",
          "start": 0,
          "username": "fan_rbq"
        }
      ]
    },
    "geo": {},
    "id": "2054647801544683564",
    "in_reply_to_user_id": "1426079620906975232",
    "lang": "zh",
    "note_tweet": {
      "entities": {}
    },
    "possibly_sensitive": false,
    "public_metrics": {
      "bookmark_count": 0,
      "impression_count": 0,
      "like_count": 0,
      "quote_count": 0,
      "reply_count": 0,
      "retweet_count": 0
    },
    "referenced_tweets": [
      {
        "id": "2054056616732041493",
        "type": "replied_to"
      }
    ],
    "reply_settings": "everyone",
    "text": "@fan_rbq 我刚入圈的时候完全不知道，瞎搞，最后就是六十多，也没有效果，太神秘了……我在吃糯米壳吗"
  },
  "includes": {
    "tweets": [
      {
        "article": {},
        "attachments": {},
        "author_id": "1804875241367433216",
        "conversation_id": "2054008553992753563",
        "created_at": "2026-05-13T19:39:44.000Z",
        "edit_controls": {
          "editable_until": "2026-05-13T20:39:44.000Z",
          "edits_remaining": 5,
          "is_edit_eligible": false
        },
        "edit_history_tweet_ids": [
          "2054647801544683564"
        ],
        "entities": {
          "mentions": [
            {
              "end": 8,
              "id": "1426079620906975232",
              "start": 0,
              "username": "fan_rbq"
            }
          ]
        },
        "geo": {},
        "id": "2054647801544683564",
        "in_reply_to_user_id": "1426079620906975232",
        "lang": "zh",
        "note_tweet": {
          "entities": {}
        },
        "possibly_sensitive": false,
        "public_metrics": {
          "bookmark_count": 0,
          "impression_count": 0,
          "like_count": 0,
          "quote_count": 0,
          "reply_count": 0,
          "retweet_count": 0
        },
        "referenced_tweets": [
          {
            "id": "2054056616732041493",
            "type": "replied_to"
          }
        ],
        "reply_settings": "everyone",
        "text": "@fan_rbq 我刚入圈的时候完全不知道，瞎搞，最后就是六十多，也没有效果，太神秘了……我在吃糯米壳吗"
      },
      {
        "article": {},
        "attachments": {},
        "author_id": "1426079620906975232",
        "conversation_id": "2054008553992753563",
        "created_at": "2026-05-12T04:30:34.000Z",
        "edit_controls": {
          "editable_until": "2026-05-12T05:30:34.000Z",
          "edits_remaining": 5,
          "is_edit_eligible": false
        },
        "edit_history_tweet_ids": [
          "2054056616732041493"
        ],
        "entities": {
          "mentions": [
            {
              "end": 13,
              "id": "1804875241367433216",
              "start": 0,
              "username": "aberyoheiskm"
            }
          ]
        },
        "geo": {},
        "id": "2054056616732041493",
        "in_reply_to_user_id": "1804875241367433216",
        "lang": "zh",
        "note_tweet": {
          "entities": {}
        },
        "possibly_sensitive": false,
        "public_metrics": {
          "bookmark_count": 0,
          "impression_count": 33,
          "like_count": 0,
          "quote_count": 0,
          "reply_count": 0,
          "retweet_count": 0
        },
        "referenced_tweets": [
          {
            "id": "2054008553992753563",
            "type": "replied_to"
          }
        ],
        "reply_settings": "everyone",
        "text": "@aberyoheiskm 是的是的，之前我忍耐到4个小时就忍不住吃了，但是药效就没那么多了（也可能是安慰剂效应吧😔"
      }
    ],
    "users": [
      {
        "created_at": "2024-06-23T13:53:01.000Z",
        "description": "⊹ 𝚜𝚞𝚣𝚞𝚖𝚎 ⊹ 小号：@aberyoheiabe⌇𝟢𝟧⌇天使/水色界隈 🫧\nメンヘラ  ✟  依存症  ✟  OD ✟ お掃除 💉\n​*⑅୨୧  無言フォローでお迎え​  ୨୧⑅* \n仲良くしてくれる子 DM待ってます💤\n​他担・他界隈様◎同担◎( 恋愛不可 🆖)看成分互fo↓来玩提问箱！",
        "entities": {
          "description": {
            "mentions": [
              {
                "end": 27,
                "start": 14,
                "username": "aberyoheiabe"
              }
            ]
          },
          "url": {
            "urls": [
              {
                "display_url": "ngl.link/aberyoheiskm",
                "end": 23,
                "expanded_url": "https://ngl.link/aberyoheiskm",
                "start": 0,
                "url": "https://t.co/gj0HdlxzyS"
              }
            ]
          }
        },
        "id": "1804875241367433216",
        "location": "キラキラな世界ʚ✞ɞ ",
        "name": "⊹すずめ⊹🩵",
        "pinned_tweet_id": "2040494384823874007",
        "profile_image_url": "https://pbs.twimg.com/profile_images/2040630139747553280/HymSNJZ__normal.jpg",
        "protected": false,
        "public_metrics": {
          "followers_count": 207,
          "following_count": 235,
          "like_count": 2481,
          "listed_count": 1,
          "media_count": 124,
          "tweet_count": 1429
        },
        "url": "https://t.co/gj0HdlxzyS",
        "username": "aberyoheiskm",
        "verified": false
      },
      {
        "created_at": "2021-08-13T07:14:18.000Z",
        "description": "♂08  167/52  休学ing   intp  想发啥发啥👿",
        "id": "1426079620906975232",
        "name": "饭🍥",
        "profile_image_url": "https://pbs.twimg.com/profile_images/2017660079424868352/io_4mzAh_normal.jpg",
        "protected": false,
        "public_metrics": {
          "followers_count": 24,
          "following_count": 107,
          "like_count": 1093,
          "listed_count": 0,
          "media_count": 8,
          "tweet_count": 149
        },
        "username": "fan_rbq",
        "verified": false
      }
    ]
  }
}