{
  "data": {
    "article": {},
    "attachments": {},
    "author_id": "1804875241367433216",
    "conversation_id": "2042269254264013054",
    "created_at": "2026-04-10T13:17:27.000Z",
    "edit_controls": {
      "editable_until": "2026-04-10T14:17:27.000Z",
      "edits_remaining": 5,
      "is_edit_eligible": false
    },
    "edit_history_tweet_ids": [
      "2042592798214623677"
    ],
    "entities": {
      "mentions": [
        {
          "end": 8,
          "id": "1782303137136852992",
          "start": 0,
          "username": "cxxf1zh"
        },
        {
          "end": 23,
          "id": "2007534563007049735",
          "start": 9,
          "username": "HappyJumpFish"
        },
        {
          "end": 33,
          "id": "1684263981471657985",
          "start": 24,
          "username": "insdpp19"
        },
        {
          "end": 46,
          "id": "1940190746016976897",
          "start": 34,
          "username": "sakarayaner"
        }
      ]
    },
    "geo": {},
    "id": "2042592798214623677",
    "in_reply_to_user_id": "1782303137136852992",
    "lang": "ja",
    "note_tweet": {
      "entities": {}
    },
    "possibly_sensitive": false,
    "public_metrics": {
      "bookmark_count": 0,
      "impression_count": 0,
      "like_count": 0,
      "quote_count": 0,
      "reply_count": 0,
      "retweet_count": 0
    },
    "referenced_tweets": [
      {
        "id": "2042577380599042335",
        "type": "replied_to"
      }
    ],
    "reply_settings": "everyone",
    "text": "@cxxf1zh @HappyJumpFish @insdpp19 @sakarayaner 没事直接隐瞒年龄，然后化化妆装疯就看不出来了，我就是打算酱紫的ദ്ദി˶ｰ̀֊ｰ́ )✧"
  },
  "includes": {
    "tweets": [
      {
        "article": {},
        "attachments": {},
        "author_id": "1804875241367433216",
        "conversation_id": "2042269254264013054",
        "created_at": "2026-04-10T13:17:27.000Z",
        "edit_controls": {
          "editable_until": "2026-04-10T14:17:27.000Z",
          "edits_remaining": 5,
          "is_edit_eligible": false
        },
        "edit_history_tweet_ids": [
          "2042592798214623677"
        ],
        "entities": {
          "mentions": [
            {
              "end": 8,
              "id": "1782303137136852992",
              "start": 0,
              "username": "cxxf1zh"
            },
            {
              "end": 23,
              "id": "2007534563007049735",
              "start": 9,
              "username": "HappyJumpFish"
            },
            {
              "end": 33,
              "id": "1684263981471657985",
              "start": 24,
              "username": "insdpp19"
            },
            {
              "end": 46,
              "id": "1940190746016976897",
              "start": 34,
              "username": "sakarayaner"
            }
          ]
        },
        "geo": {},
        "id": "2042592798214623677",
        "in_reply_to_user_id": "1782303137136852992",
        "lang": "ja",
        "note_tweet": {
          "entities": {}
        },
        "possibly_sensitive": false,
        "public_metrics": {
          "bookmark_count": 0,
          "impression_count": 0,
          "like_count": 0,
          "quote_count": 0,
          "reply_count": 0,
          "retweet_count": 0
        },
        "referenced_tweets": [
          {
            "id": "2042577380599042335",
            "type": "replied_to"
          }
        ],
        "reply_settings": "everyone",
        "text": "@cxxf1zh @HappyJumpFish @insdpp19 @sakarayaner 没事直接隐瞒年龄，然后化化妆装疯就看不出来了，我就是打算酱紫的ദ്ദി˶ｰ̀֊ｰ́ )✧"
      },
      {
        "article": {},
        "attachments": {},
        "author_id": "1782303137136852992",
        "conversation_id": "2042269254264013054",
        "created_at": "2026-04-10T12:16:11.000Z",
        "edit_controls": {
          "editable_until": "2026-04-10T13:16:11.000Z",
          "edits_remaining": 5,
          "is_edit_eligible": false
        },
        "edit_history_tweet_ids": [
          "2042577380599042335"
        ],
        "entities": {
          "mentions": [
            {
              "end": 13,
              "id": "1804875241367433216",
              "start": 0,
              "username": "aberyoheiskm"
            },
            {
              "end": 28,
              "id": "2007534563007049735",
              "start": 14,
              "username": "HappyJumpFish"
            },
            {
              "end": 38,
              "id": "1684263981471657985",
              "start": 29,
              "username": "insdpp19"
            },
            {
              "end": 51,
              "id": "1940190746016976897",
              "start": 39,
              "username": "sakarayaner"
            }
          ]
        },
        "geo": {},
        "id": "2042577380599042335",
        "in_reply_to_user_id": "1804875241367433216",
        "lang": "zh",
        "note_tweet": {
          "entities": {}
        },
        "possibly_sensitive": false,
        "public_metrics": {
          "bookmark_count": 0,
          "impression_count": 23,
          "like_count": 2,
          "quote_count": 0,
          "reply_count": 1,
          "retweet_count": 0
        },
        "referenced_tweets": [
          {
            "id": "2042576147020681676",
            "type": "replied_to"
          }
        ],
        "reply_settings": "everyone",
        "text": "@aberyoheiskm @HappyJumpFish @insdpp19 @sakarayaner 我发誓一入籍就去当东横kids(虽然到时候可能已经不是kids了😢"
      }
    ],
    "users": [
      {
        "created_at": "2024-06-23T13:53:01.000Z",
        "description": "⊹ 𝚜𝚞𝚣𝚞𝚖𝚎 ⊹ 不安所以到处评论见谅⌇𝟢𝟧⌇天使/水色界隈 🫧\nメンヘラ  ✟  依存症  ✟  OD ✟ お掃除 💉\n​*⑅୨୧  無言フォローでお迎え​  ୨୧⑅* \n仲良くしてくれる子 DM待ってます💤\n​他担・他界隈様  ◎  同担  ◎( 恋愛不可 🆖)看成分回fo↓来提问箱！",
        "entities": {
          "url": {
            "urls": [
              {
                "display_url": "ngl.link/aberyoheiskm",
                "end": 23,
                "expanded_url": "https://ngl.link/aberyoheiskm",
                "start": 0,
                "url": "https://t.co/gj0HdlxzyS"
              }
            ]
          }
        },
        "id": "1804875241367433216",
        "location": "キラキラな世界ʚ✞ɞ ",
        "name": "⊹すずめ⊹🩵",
        "pinned_tweet_id": "2040494384823874007",
        "profile_image_url": "https://pbs.twimg.com/profile_images/2040630139747553280/HymSNJZ__normal.jpg",
        "protected": false,
        "public_metrics": {
          "followers_count": 59,
          "following_count": 124,
          "like_count": 789,
          "listed_count": 0,
          "media_count": 44,
          "tweet_count": 506
        },
        "url": "https://t.co/gj0HdlxzyS",
        "username": "aberyoheiskm",
        "verified": false
      },
      {
        "created_at": "2024-04-22T06:59:28.000Z",
        "description": "是个INFP-T音乐制作人/DJ/下北沢传奇吉他手(勉強中😉",
        "id": "1782303137136852992",
        "location": "Suginami-ku, Tokyo",
        "name": "一澤子",
        "pinned_tweet_id": "2035385903506759842",
        "profile_image_url": "https://pbs.twimg.com/profile_images/2041814931683848192/zcl-cu0Y_normal.jpg",
        "protected": false,
        "public_metrics": {
          "followers_count": 44,
          "following_count": 74,
          "like_count": 970,
          "listed_count": 0,
          "media_count": 87,
          "tweet_count": 392
        },
        "username": "cxxf1zh",
        "verified": false
      },
      {
        "created_at": "2026-01-03T19:29:13.000Z",
        "description": "魔方速拧爱好者，喜欢吉他，喜欢看书，喜欢写点短篇小说，尤其喜欢村上春树\n一名16岁男高中生，为留学的困难事业热情奋斗中，不希望与没有素质礼貌的人沟通，希望我们能友善地一起交流，很希望成为你的朋友",
        "id": "2007534563007049735",
        "name": "Liyuexuan",
        "pinned_tweet_id": "2041961360884375864",
        "profile_image_url": "https://pbs.twimg.com/profile_images/2007534827684409344/L95ruiQK_normal.jpg",
        "protected": false,
        "public_metrics": {
          "followers_count": 9,
          "following_count": 34,
          "like_count": 99,
          "listed_count": 0,
          "media_count": 1,
          "tweet_count": 83
        },
        "username": "HappyJumpFish",
        "verified": false
      },
      {
        "created_at": "2023-07-26T18:06:48.000Z",
        "description": "。",
        "id": "1684263981471657985",
        "location": "nagasaki Japan",
        "name": "。",
        "profile_image_url": "https://pbs.twimg.com/profile_images/1918606792415973377/NgWlsZiV_normal.jpg",
        "protected": false,
        "public_metrics": {
          "followers_count": 5,
          "following_count": 56,
          "like_count": 222,
          "listed_count": 0,
          "media_count": 1,
          "tweet_count": 45
        },
        "username": "insdpp19",
        "verified": false
      },
      {
        "created_at": "2025-07-01T23:28:26.000Z",
        "description": "i 🩶 uuu so @in2dkira | coser | 舞萌| 不闲聊",
        "entities": {
          "description": {
            "mentions": [
              {
                "end": 20,
                "start": 11,
                "username": "in2dkira"
              }
            ]
          }
        },
        "id": "1940190746016976897",
        "location": "🚪88/188/520",
        "name": "sakara",
        "pinned_tweet_id": "2041544288291725341",
        "profile_image_url": "https://pbs.twimg.com/profile_images/2032452412095750145/e_dC_gVT_normal.jpg",
        "protected": false,
        "public_metrics": {
          "followers_count": 221,
          "following_count": 43,
          "like_count": 810,
          "listed_count": 1,
          "media_count": 54,
          "tweet_count": 162
        },
        "username": "sakarayaner",
        "verified": false
      }
    ]
  }
}