{
  "data": {
    "article": {},
    "attachments": {},
    "author_id": "1804875241367433216",
    "conversation_id": "2042982310795219238",
    "created_at": "2026-04-22T18:45:50.000Z",
    "edit_controls": {
      "editable_until": "2026-04-22T19:45:50.000Z",
      "edits_remaining": 5,
      "is_edit_eligible": false
    },
    "edit_history_tweet_ids": [
      "2047024094630330769"
    ],
    "entities": {
      "mentions": [
        {
          "end": 13,
          "id": "2043241256680067072",
          "start": 0,
          "username": "Cuisclx_0816"
        },
        {
          "end": 27,
          "id": "1934885525657165824",
          "start": 14,
          "username": "ooxygen_6305"
        },
        {
          "end": 36,
          "id": "2025905993935405057",
          "start": 28,
          "username": "ganzeos"
        },
        {
          "end": 49,
          "id": "2008812080099672064",
          "start": 37,
          "username": "Xiaoyi_0324"
        }
      ]
    },
    "geo": {},
    "id": "2047024094630330769",
    "in_reply_to_user_id": "2043241256680067072",
    "lang": "zh",
    "note_tweet": {
      "entities": {}
    },
    "possibly_sensitive": false,
    "public_metrics": {
      "bookmark_count": 0,
      "impression_count": 0,
      "like_count": 0,
      "quote_count": 0,
      "reply_count": 0,
      "retweet_count": 0
    },
    "referenced_tweets": [
      {
        "id": "2046758710178091117",
        "type": "replied_to"
      }
    ],
    "reply_settings": "everyone",
    "text": "@Cuisclx_0816 @ooxygen_6305 @ganzeos @Xiaoyi_0324 果咩纳塞才看到消息😭下午有人试了说这个处方不能用呜呜呜呜恐怕帮不上忙了……"
  },
  "includes": {
    "tweets": [
      {
        "article": {},
        "attachments": {},
        "author_id": "1804875241367433216",
        "conversation_id": "2042982310795219238",
        "created_at": "2026-04-22T18:45:50.000Z",
        "edit_controls": {
          "editable_until": "2026-04-22T19:45:50.000Z",
          "edits_remaining": 5,
          "is_edit_eligible": false
        },
        "edit_history_tweet_ids": [
          "2047024094630330769"
        ],
        "entities": {
          "mentions": [
            {
              "end": 13,
              "id": "2043241256680067072",
              "start": 0,
              "username": "Cuisclx_0816"
            },
            {
              "end": 27,
              "id": "1934885525657165824",
              "start": 14,
              "username": "ooxygen_6305"
            },
            {
              "end": 36,
              "id": "2025905993935405057",
              "start": 28,
              "username": "ganzeos"
            },
            {
              "end": 49,
              "id": "2008812080099672064",
              "start": 37,
              "username": "Xiaoyi_0324"
            }
          ]
        },
        "geo": {},
        "id": "2047024094630330769",
        "in_reply_to_user_id": "2043241256680067072",
        "lang": "zh",
        "note_tweet": {
          "entities": {}
        },
        "possibly_sensitive": false,
        "public_metrics": {
          "bookmark_count": 0,
          "impression_count": 0,
          "like_count": 0,
          "quote_count": 0,
          "reply_count": 0,
          "retweet_count": 0
        },
        "referenced_tweets": [
          {
            "id": "2046758710178091117",
            "type": "replied_to"
          }
        ],
        "reply_settings": "everyone",
        "text": "@Cuisclx_0816 @ooxygen_6305 @ganzeos @Xiaoyi_0324 果咩纳塞才看到消息😭下午有人试了说这个处方不能用呜呜呜呜恐怕帮不上忙了……"
      },
      {
        "article": {},
        "attachments": {},
        "author_id": "2043241256680067072",
        "conversation_id": "2042982310795219238",
        "created_at": "2026-04-22T01:11:18.000Z",
        "edit_controls": {
          "editable_until": "2026-04-22T02:11:18.000Z",
          "edits_remaining": 5,
          "is_edit_eligible": false
        },
        "edit_history_tweet_ids": [
          "2046758710178091117"
        ],
        "entities": {
          "mentions": [
            {
              "end": 13,
              "id": "1804875241367433216",
              "start": 0,
              "username": "aberyoheiskm"
            },
            {
              "end": 27,
              "id": "1934885525657165824",
              "start": 14,
              "username": "ooxygen_6305"
            },
            {
              "end": 36,
              "id": "2025905993935405057",
              "start": 28,
              "username": "ganzeos"
            },
            {
              "end": 49,
              "id": "2008812080099672064",
              "start": 37,
              "username": "Xiaoyi_0324"
            }
          ]
        },
        "geo": {},
        "id": "2046758710178091117",
        "in_reply_to_user_id": "1804875241367433216",
        "lang": "ja",
        "note_tweet": {
          "entities": {}
        },
        "possibly_sensitive": false,
        "public_metrics": {
          "bookmark_count": 0,
          "impression_count": 31,
          "like_count": 0,
          "quote_count": 0,
          "reply_count": 0,
          "retweet_count": 0
        },
        "referenced_tweets": [
          {
            "id": "2044829958451892311",
            "type": "replied_to"
          }
        ],
        "reply_settings": "everyone",
        "text": "@aberyoheiskm @ooxygen_6305 @ganzeos @Xiaoyi_0324 宝宝求…"
      }
    ],
    "users": [
      {
        "created_at": "2024-06-23T13:53:01.000Z",
        "description": "⊹ 𝚜𝚞𝚣𝚞𝚖𝚎 ⊹ 不安所以到处评论见谅⌇逃离墙内中⌇𝟢𝟧⌇天使/水色界隈 🫧\nメンヘラ  ✟  依存症  ✟  OD ✟ お掃除 💉\n​*⑅୨୧  無言フォローでお迎え​  ୨୧⑅* \n仲良くしてくれる子 DM待ってます💤\n​他担・他界隈様◎同担◎( 恋愛不可 🆖)看成分互fo↓来玩提问箱！",
        "entities": {
          "url": {
            "urls": [
              {
                "display_url": "ngl.link/aberyoheiskm",
                "end": 23,
                "expanded_url": "https://ngl.link/aberyoheiskm",
                "start": 0,
                "url": "https://t.co/gj0HdlxzyS"
              }
            ]
          }
        },
        "id": "1804875241367433216",
        "location": "キラキラな世界ʚ✞ɞ ",
        "name": "⊹すずめ⊹🩵",
        "pinned_tweet_id": "2040494384823874007",
        "profile_image_url": "https://pbs.twimg.com/profile_images/2040630139747553280/HymSNJZ__normal.jpg",
        "protected": false,
        "public_metrics": {
          "followers_count": 130,
          "following_count": 181,
          "like_count": 2021,
          "listed_count": 0,
          "media_count": 84,
          "tweet_count": 1130
        },
        "url": "https://t.co/gj0HdlxzyS",
        "username": "aberyoheiskm",
        "verified": false
      },
      {
        "created_at": "2026-04-12T08:16:10.000Z",
        "description": "如果幸福像流泪一样简单就好了",
        "id": "2043241256680067072",
        "name": "upset",
        "profile_image_url": "https://pbs.twimg.com/profile_images/2046466609389457408/krkpTYpZ_normal.jpg",
        "protected": false,
        "public_metrics": {
          "followers_count": 16,
          "following_count": 27,
          "like_count": 64,
          "listed_count": 0,
          "media_count": 1,
          "tweet_count": 68
        },
        "username": "Cuisclx_0816",
        "verified": false
      },
      {
        "created_at": "2025-06-17T08:07:35.000Z",
        "description": "07intp 🌈m0.4",
        "id": "1934885525657165824",
        "name": "Silas Valle",
        "profile_image_url": "https://pbs.twimg.com/profile_images/2040899815656304641/s4AF9_RM_normal.jpg",
        "protected": false,
        "public_metrics": {
          "followers_count": 10,
          "following_count": 45,
          "like_count": 2485,
          "listed_count": 0,
          "media_count": 2,
          "tweet_count": 108
        },
        "username": "ooxygen_6305",
        "verified": false
      },
      {
        "created_at": "2026-02-23T12:10:11.000Z",
        "description": "我叫甘泽\n直男（不顺直\n坐标浙江宁波\n生日12.24\n08年摩羯座isfj\n喜欢玩游戏/第五人格/王者荣耀/vrchat/我的世界（java）\n喜欢永雏塔菲，不追星、不怎么磕cp、🈚雷点（小粉红走开\n本人性格温良（除了游戏里面？！不过不会去骂朋友）\n可以找我玩游戏",
        "id": "2025905993935405057",
        "name": "甘泽",
        "profile_image_url": "https://pbs.twimg.com/profile_images/2033580678949044224/XHsXnzKL_normal.jpg",
        "protected": false,
        "public_metrics": {
          "followers_count": 7,
          "following_count": 14,
          "like_count": 31,
          "listed_count": 0,
          "media_count": 1,
          "tweet_count": 16
        },
        "username": "ganzeos",
        "verified": false
      },
      {
        "created_at": "2026-01-07T08:05:14.000Z",
        "description": "几乎全天在线的互联网飞舞!负面情绪/碎碎念致歉|直fo成分回|同类直接回(没看到要私信🥹|MTX(F?)|里推@NiaoYou83766|👇匿名提问|或许是个心理委员|详细BIO在置顶",
        "entities": {
          "description": {
            "mentions": [
              {
                "end": 68,
                "start": 55,
                "username": "NiaoYou83766"
              }
            ]
          },
          "url": {
            "urls": [
              {
                "display_url": "ngl.link/xiaoyi0324",
                "end": 23,
                "expanded_url": "https://ngl.link/xiaoyi0324",
                "start": 0,
                "url": "https://t.co/SiMjjU6DSn"
              }
            ]
          }
        },
        "id": "2008812080099672064",
        "location": "来玩捉迷藏吧？",
        "name": "樱川由奈🏳️‍⚧️sakura🍥",
        "pinned_tweet_id": "2047000942542028836",
        "profile_image_url": "https://pbs.twimg.com/profile_images/2041966864163880960/7aHicZzs_normal.jpg",
        "protected": false,
        "public_metrics": {
          "followers_count": 346,
          "following_count": 170,
          "like_count": 1138,
          "listed_count": 0,
          "media_count": 149,
          "tweet_count": 1109
        },
        "url": "https://t.co/SiMjjU6DSn",
        "username": "Xiaoyi_0324",
        "verified": false
      }
    ]
  }
}