{
  "data": {
    "article": {},
    "attachments": {},
    "author_id": "1804875241367433216",
    "conversation_id": "2053399588216971423",
    "created_at": "2026-05-10T15:31:34.000Z",
    "edit_controls": {
      "editable_until": "2026-05-10T16:31:34.000Z",
      "edits_remaining": 5,
      "is_edit_eligible": false
    },
    "edit_history_tweet_ids": [
      "2053498186715820516"
    ],
    "entities": {
      "mentions": [
        {
          "end": 12,
          "id": "2052760341411708928",
          "start": 0,
          "username": "Sui17171Fei"
        }
      ]
    },
    "geo": {},
    "id": "2053498186715820516",
    "in_reply_to_user_id": "2052760341411708928",
    "lang": "zh",
    "note_tweet": {
      "entities": {}
    },
    "possibly_sensitive": false,
    "public_metrics": {
      "bookmark_count": 0,
      "impression_count": 0,
      "like_count": 0,
      "quote_count": 0,
      "reply_count": 0,
      "retweet_count": 0
    },
    "referenced_tweets": [
      {
        "id": "2053430007519957032",
        "type": "replied_to"
      }
    ],
    "reply_settings": "everyone",
    "text": "@Sui17171Fei 不知道为什么这几天非常低精力……低到列表的消息都没回，x都没上线，上次从漫展回来的东西到现在都没整理完orz……看到千早这么安慰真的好感动有心了呜呜呜我会好好休息的……！今天晚上打算先到空腹六小时了然后进行一个d的○……🤤"
  },
  "includes": {
    "media": [
      {
        "height": 280,
        "media_key": "16_2053429996195364864",
        "preview_image_url": "https://pbs.twimg.com/tweet_video_thumb/HH8_s7ZbQAADE_B.jpg",
        "public_metrics": {},
        "type": "animated_gif",
        "variants": [
          {
            "bit_rate": 0,
            "content_type": "video/mp4",
            "url": "https://video.twimg.com/tweet_video/HH8_s7ZbQAADE_B.mp4"
          }
        ],
        "width": 498
      }
    ],
    "tweets": [
      {
        "article": {},
        "attachments": {},
        "author_id": "1804875241367433216",
        "conversation_id": "2053399588216971423",
        "created_at": "2026-05-10T15:31:34.000Z",
        "edit_controls": {
          "editable_until": "2026-05-10T16:31:34.000Z",
          "edits_remaining": 5,
          "is_edit_eligible": false
        },
        "edit_history_tweet_ids": [
          "2053498186715820516"
        ],
        "entities": {
          "mentions": [
            {
              "end": 12,
              "id": "2052760341411708928",
              "start": 0,
              "username": "Sui17171Fei"
            }
          ]
        },
        "geo": {},
        "id": "2053498186715820516",
        "in_reply_to_user_id": "2052760341411708928",
        "lang": "zh",
        "note_tweet": {
          "entities": {}
        },
        "possibly_sensitive": false,
        "public_metrics": {
          "bookmark_count": 0,
          "impression_count": 0,
          "like_count": 0,
          "quote_count": 0,
          "reply_count": 0,
          "retweet_count": 0
        },
        "referenced_tweets": [
          {
            "id": "2053430007519957032",
            "type": "replied_to"
          }
        ],
        "reply_settings": "everyone",
        "text": "@Sui17171Fei 不知道为什么这几天非常低精力……低到列表的消息都没回，x都没上线，上次从漫展回来的东西到现在都没整理完orz……看到千早这么安慰真的好感动有心了呜呜呜我会好好休息的……！今天晚上打算先到空腹六小时了然后进行一个d的○……🤤"
      },
      {
        "article": {},
        "attachments": {
          "media_keys": [
            "16_2053429996195364864"
          ]
        },
        "author_id": "2052760341411708928",
        "conversation_id": "2053399588216971423",
        "created_at": "2026-05-10T11:00:39.000Z",
        "edit_controls": {
          "editable_until": "2026-05-10T12:00:39.000Z",
          "edits_remaining": 5,
          "is_edit_eligible": false
        },
        "edit_history_tweet_ids": [
          "2053430007519957032"
        ],
        "entities": {
          "mentions": [
            {
              "end": 13,
              "id": "1804875241367433216",
              "start": 0,
              "username": "aberyoheiskm"
            }
          ],
          "urls": [
            {
              "display_url": "pic.x.com/bfjNTW6e2z",
              "end": 166,
              "expanded_url": "https://x.com/Sui17171Fei/status/2053430007519957032/photo/1",
              "media_key": "16_2053429996195364864",
              "start": 143,
              "url": "https://t.co/bfjNTW6e2z"
            }
          ]
        },
        "geo": {},
        "id": "2053430007519957032",
        "in_reply_to_user_id": "1804875241367433216",
        "lang": "zh",
        "note_tweet": {
          "entities": {}
        },
        "possibly_sensitive": false,
        "public_metrics": {
          "bookmark_count": 0,
          "impression_count": 12,
          "like_count": 0,
          "quote_count": 0,
          "reply_count": 0,
          "retweet_count": 0
        },
        "referenced_tweets": [
          {
            "id": "2053399917985677466",
            "type": "replied_to"
          }
        ],
        "reply_settings": "everyone",
        "text": "@aberyoheiskm 太过疲惫了吧，应该在不知不觉间在某些事情上努力过度了，但是自己又没有察觉到自己的付出，才会导致莫名其妙的劳累吧，嘛嘛休息吧，毕竟人会常常否定自己的努力，或者觉得自己做的不够，所以才会劳累的嘛，所以实际上你已经做得足够好了喔，可能自己发现不了，所以嘛先休息吧 https://t.co/bfjNTW6e2z"
      }
    ],
    "users": [
      {
        "created_at": "2024-06-23T13:53:01.000Z",
        "description": "⊹ 𝚜𝚞𝚣𝚞𝚖𝚎 ⊹ 小号：@aberyoheiabe⌇𝟢𝟧⌇天使/水色界隈 🫧\nメンヘラ  ✟  依存症  ✟  OD ✟ お掃除 💉\n​*⑅୨୧  無言フォローでお迎え​  ୨୧⑅* \n仲良くしてくれる子 DM待ってます💤\n​他担・他界隈様◎同担◎( 恋愛不可 🆖)看成分互fo↓来玩提问箱！",
        "entities": {
          "description": {
            "mentions": [
              {
                "end": 27,
                "start": 14,
                "username": "aberyoheiabe"
              }
            ]
          },
          "url": {
            "urls": [
              {
                "display_url": "ngl.link/aberyoheiskm",
                "end": 23,
                "expanded_url": "https://ngl.link/aberyoheiskm",
                "start": 0,
                "url": "https://t.co/gj0HdlxzyS"
              }
            ]
          }
        },
        "id": "1804875241367433216",
        "location": "キラキラな世界ʚ✞ɞ ",
        "name": "⊹すずめ⊹🩵",
        "pinned_tweet_id": "2040494384823874007",
        "profile_image_url": "https://pbs.twimg.com/profile_images/2040630139747553280/HymSNJZ__normal.jpg",
        "protected": false,
        "public_metrics": {
          "followers_count": 198,
          "following_count": 242,
          "like_count": 2376,
          "listed_count": 1,
          "media_count": 123,
          "tweet_count": 1356
        },
        "url": "https://t.co/gj0HdlxzyS",
        "username": "aberyoheiskm",
        "verified": false
      },
      {
        "created_at": "2026-05-08T14:39:47.000Z",
        "description": "是千早的姐姐大人千岁/药理学习中/可以称为千岁/心理学重度依赖/魔法少女千岁/LGBT全友好/提供自杀干预思路详解",
        "id": "2052760341411708928",
        "name": "妃宫千早",
        "pinned_tweet_id": "2053188472073281774",
        "profile_image_url": "https://pbs.twimg.com/profile_images/2053203840141500416/0ozHzqR0_normal.jpg",
        "protected": false,
        "public_metrics": {
          "followers_count": 134,
          "following_count": 1,
          "like_count": 1,
          "listed_count": 0,
          "media_count": 29,
          "tweet_count": 105
        },
        "username": "Sui17171Fei",
        "verified": false
      }
    ]
  }
}